TornadoTcpProgram/README.md
TornadoTcpProgram/__init__.py
TornadoTcpProgram/__main__.py
TornadoTcpProgram/file.epub
TornadoTcpProgram/index.html
TornadoTcpProgram/css/__init__.py
TornadoTcpProgram/css/annotations.css
TornadoTcpProgram/css/main.css
TornadoTcpProgram/css/normalize.css
TornadoTcpProgram/css/popup.css
TornadoTcpProgram/font/__init__.py
TornadoTcpProgram/font/fontello.eot
TornadoTcpProgram/font/fontello.svg
TornadoTcpProgram/font/fontello.ttf
TornadoTcpProgram/font/fontello.woff
TornadoTcpProgram/img/__init__.py
TornadoTcpProgram/img/annotator-glyph-sprite.png
TornadoTcpProgram/img/annotator-icon-sprite.png
TornadoTcpProgram/img/apple-touch-icon.png
TornadoTcpProgram/img/cancelfullscreen.png
TornadoTcpProgram/img/close.png
TornadoTcpProgram/img/fullscreen.png
TornadoTcpProgram/img/loader.gif
TornadoTcpProgram/img/menu-icon.png
TornadoTcpProgram/img/save.png
TornadoTcpProgram/img/saved.png
TornadoTcpProgram/img/settings-s.png
TornadoTcpProgram/img/settings.png
TornadoTcpProgram/img/star.png
TornadoTcpProgram/js/__init__.py
TornadoTcpProgram/js/epub.js
TornadoTcpProgram/js/epub.min.js
TornadoTcpProgram/js/epub.min.map
TornadoTcpProgram/js/hooks.min.js
TornadoTcpProgram/js/hooks.min.map
TornadoTcpProgram/js/reader.js
TornadoTcpProgram/js/reader.js.map
TornadoTcpProgram/js/reader.min.js
TornadoTcpProgram/js/reader.min.map
TornadoTcpProgram/js/hooks/__init__.py
TornadoTcpProgram/js/hooks/extensions/__init__.py
TornadoTcpProgram/js/hooks/extensions/highlight.js
TornadoTcpProgram/js/libs/__init__.py
TornadoTcpProgram/js/libs/jquery.min.js
TornadoTcpProgram/js/libs/localforage.min.js
TornadoTcpProgram/js/libs/screenfull.js
TornadoTcpProgram/js/libs/screenfull.min.js
TornadoTcpProgram/js/libs/zip.min.js
TornadoTcpProgram/js/plugins/__init__.py
TornadoTcpProgram/js/plugins/hypothesis.js
TornadoTcpProgram/js/plugins/search.js
tornado_tcp_program-2024.3.4.0.dist-info/METADATA
tornado_tcp_program-2024.3.4.0.dist-info/WHEEL
tornado_tcp_program-2024.3.4.0.dist-info/entry_points.txt
tornado_tcp_program-2024.3.4.0.dist-info/top_level.txt
tornado_tcp_program-2024.3.4.0.dist-info/RECORD
